smlp/PreProcessing.py
smlp/Thesaurus.py
smlp/__init__.py
smlp/unicov.py
smlp/data/idf.txt
smlp/data/stopwords.txt
smlp/data/test.txt
smlp/data/tmp.txt
smlp/data/token.dict
smlp/data/userdict
smlp/data/wdic.txt
smlp/models/__init__.py
smlp/models/lung_cancer.py
smlp-1.1.0.dist-info/METADATA
smlp-1.1.0.dist-info/WHEEL
smlp-1.1.0.dist-info/top_level.txt
smlp-1.1.0.dist-info/RECORD
