Metadata-Version: 2.1
Name: smlp
Version: 1.1.0
Summary: a shallow machine learning toolkit for text PreProcessing
Home-page: https://github.com/cbai066
Author: Carl Bai
Author-email: carlbai66@gmail.com
License: MIT
Keywords: shallow_machine_learning_platform nlp machine_learning jieba segment segments encoding serving
Platform: UNKNOWN
Classifier: Programming Language :: Python :: 3.4
Classifier: Programming Language :: Python :: 3.5
Classifier: Programming Language :: Python :: 3.6
Classifier: Programming Language :: Python :: 3.7
Classifier: License :: OSI Approved :: MIT License
Classifier: Operating System :: OS Independent
Requires-Dist: numpy
Requires-Dist: jieba
Requires-Dist: textrank4zh
Requires-Dist: pandas
Requires-Dist: tqdm
Requires-Dist: pytest
Provides-Extra: http
Requires-Dist: flask ; extra == 'http'
Requires-Dist: flask-compress ; extra == 'http'
Requires-Dist: flask-cors ; extra == 'http'
Requires-Dist: flask-json ; extra == 'http'
